dcmfetch/__init__.py
dcmfetch/aettable.py
dcmfetch/dcmfetch.py
dcmfetch/dcmfetchtool.py
dcmfetch/dicomweb.py
dcmfetch/fetchdialog.py
dcmfetch/qidcm4che3.py
dcmfetch/qimock.py
dcmfetch/qipynetdicom.py
dcmfetch/queryinterface.py
dcmfetch/structures.py
dcmfetch/version.py
dcmfetch/ext/dcmnodes.cf
dcmfetch/ext/findscu
dcmfetch/ext/findscu.exe
dcmfetch/ext/getscu
dcmfetch/ext/getscu.exe
dcmfetch/ext/store-tcs.properties
dcmfetch-0.3.2.dist-info/licenses/LICENCE
dcmfetch-0.3.2.dist-info/METADATA
dcmfetch-0.3.2.dist-info/WHEEL
dcmfetch-0.3.2.dist-info/entry_points.txt
dcmfetch-0.3.2.dist-info/top_level.txt
dcmfetch-0.3.2.dist-info/RECORD
