Metadata-Version: 2.4
Name: dcmfetch
Version: 0.3.2
Summary: DICOM query retrieve tools
Home-page: https://bitbucket.org/rtrhd/dcmfetch
Download-URL: https://bitbucket.org/rtrhd/dcmfetch/get/v0.3.2.zip
Author: Ron Hartley-Davies
Author-email: R.Hartley-Davies@physics.org
License: MIT
Classifier: Development Status :: 4 - Beta
Classifier: Environment :: Console
Classifier: Intended Audience :: Science/Research
Classifier: Topic :: Scientific/Engineering :: Medical Science Apps.
Classifier: Operating System :: POSIX
Classifier: Operating System :: Microsoft :: Windows
Classifier: Programming Language :: Python :: 3.10
Classifier: Programming Language :: Python :: 3.11
Classifier: Programming Language :: Python :: 3.12
Classifier: Programming Language :: Python :: 3.13
License-File: LICENCE
Requires-Dist: requests>=2.2.5
Requires-Dist: QtPy>=2.0.0
Requires-Dist: pydicom>=2.2.2
Provides-Extra: pynetdicom
Requires-Dist: pynetdicom>=2.1.1; extra == "pynetdicom"
Provides-Extra: test
Requires-Dist: cryptography; extra == "test"
Requires-Dist: pynetdicom; extra == "test"
Dynamic: author
Dynamic: author-email
Dynamic: classifier
Dynamic: description
Dynamic: description-content-type
Dynamic: download-url
Dynamic: home-page
Dynamic: license
Dynamic: license-file
Dynamic: provides-extra
Dynamic: requires-dist
Dynamic: summary
